{
  "mi-bs":{
    "nodes":{
      "First Year":[
        "BIOA01H3",
        "BIOA02H3",
        "AND-BIOA01H3-BIOA02H3"
      ]
    },
    "edges":{
      "andpre":[
        "AND-BIOA01H3-BIOA02H3<BIOA01H3",
        "AND-BIOA01H3-BIOA02H3<BIOA02H3"
      ],
      "correq":[

      ],
      "recommend":[

      ],
      "orpre":[

      ]
    }
  },
  "mj-pbs":{
    "nodes":{
      "First Year":[
        "BIOA01H3",
        "BIOA02H3",
        "CHMA10H3",
        "CHMA11H3",
        "STAB22H3",
        "PSYB07H3",
        "OR-STAB22H3-PSYB07H3",
        "AND-BIOA01H3-BIOA02H3",
        "AND-CHMA10H3-CHMA11H3"
      ],
      "Second Year":[
        "BIOB10H3",
        "BIOB11H3",
        "BIOB38H3",
        "BIOB50H3",
        "BIOB51H3",
        "BIOB12H3",
        "BIOB52H3",
        "OR-BIOB12H3-BIOB52H3"
      ],
      "Third Year":[
        "BIOC31H3",
        "BIOC37H3",
        "BIOC40H3",
        "BIOC15H3",
        "BIOC17H3",
        "BIOC50H3",
        "BIOC12H3",
        "BIOC16H3",
        "BIOC39H3"
      ],
      "Third/Fourth Year":[
        "BIOC61H3",
        "BIOD21H3",
        "BIOD37H3",
        "BIOD62H3",
        "BIOD26H3"
      ],
      "Fourth Year":[
        "BIOD30H3",
        "BIOC99H3",
        "BIOD95H3",
        "BIOD98Y3",
        "BIOD99Y3"
      ]
    },
    "edges":{
      "andpre":[
        "BIOB10H3<AND-BIOA01H3-BIOA02H3",
        "BIOB10H3<AND-CHMA10H3-CHMA11H3",
        "BIOB11H3<BIOB10H3",
        "BIOB38H3<AND-BIOA01H3-BIOA02H3",
        "BIOB50H3<AND-BIOA01H3-BIOA02H3",
        "BIOB51H3<AND-BIOA01H3-BIOA02H3",
        "BIOB12H3<AND-CHMA10H3-CHMA11H3",
        "BIOB52H3<AND-BIOA01H3-BIOA02H3",
        "BIOC31H3<BIOB11H3",
        "BIOC40H3<BIOB11H3",
        "BIOC15H3<BIOB11H3",
        "BIOC15H3<OR-STAB22H3-PSYB07H3",
        "BIOC17H3<BIOB11H3",
        "BIOC50H3<BIOB50H3",
        "BIOC50H3<BIOB51H3",
        "BIOC61H3<BIOB50H3",
        "BIOD21H3<BIOB12H3",
        "BIOD21H3<BIOC15H3",
        "BIOD21H3<BIOC17H3",
        "BIOD30H3<BIOB38H3",
        "AND-BIOA01H3-BIOA02H3<BIOA01H3",
        "AND-BIOA01H3-BIOA02H3<BIOA02H3",
        "AND-CHMA10H3-CHMA11H3<CHMA10H3",
        "AND-CHMA10H3-CHMA11H3<CHMA11H3",
        "OR-STAB22H3-PSYB07H3<STAB22H3",
        "OR-STAB22H3-PSYB07H3<PSYB07H3",
        "OR-BIOB12H3-BIOB52H3<BIOB12H3",
        "OR-BIOB12H3-BIOB52H3<BIOB52H3"
      ],
      "correq":[
        "BIOB12H3<BIOB11H3",
        "BIOB52H3<BIOB50H3",
        "BIOB52H3<BIOB51H3",
        "BIOD21H3<BIOC12H3"
      ],
      "recommend":[

      ],
      "orpre":[
        "BIOC37H3<BIOB38H3",
        "BIOC37H3<BIOB50H3",
        "BIOC37H3<BIOB51H3",
        "BIOD37H3<BIOC31H3",
        "BIOD37H3<BIOC40H3",
        "BIOD62H3<BIOC16H3",
        "BIOD62H3<BIOC50H3",
        "BIOD26H3<BIOC17H3",
        "BIOD26H3<BIOC39H3",
        "BIOD30H3<BIOC15H3",
        "BIOD30H3<BIOC31H3",
        "BIOD30H3<BIOC37H3",
        "BIOD30H3<BIOC40H3"
      ]
    }
  },
  "mj-mbids":{
    "nodes":{
      "First Year":[
        "BIOA01H3",
        "BIOA02H3",
        "CHMA10H3",
        "CHMA11H3",
        "MATA29H3",
        "MATA30H3",
        "STAB22H3",
        "PSYB07H3",
        "AND-BIOA01H3-BIOA02H3",
        "AND-CHMA10H3-CHMA11H3",
        "OR-MATA29H3-MATA30H3-STAB22H3-PSYB07H3"
      ],
      "Second Year":[
        "BIOB10H3",
        "BIOB11H3",
        "BIOB34H3",
        "BIOB50H3",
        "BIOB51H3",
        "BIOB12H3",
        "BIOB32H3",
        "BIOB33H3",
        "OR-BIOB12H3-BIOB32H3-BIOB33H3",
        "CHMB41H3",
        "CHMB42H3"
      ],
      "Third/Fourth Year":[
        "BIOC17H3",
        "BIOC20H3",
        "BIOC39H3",
        "BIOC10H3",
        "BIOC12H3",
        "BIOC13H3",
        "BIOC14H3",
        "BIOC15H3",
        "BIOC19H3",
        "BIOC31H3",
        "BIOC35H3",
        "BIOD12H3",
        "BIOD17H3",
        "BIOD19H3",
        "BIOD20H3",
        "BIOD23H3",
        "BIOD25H3",
        "BIOD26H3",
        "BIOD27H3",
        "BIOD29H3"
      ]
    },
    "edges":{
      "andpre":[
        "BIOB10H3<AND-BIOA01H3-BIOA02H3",
        "BIOB10H3<AND-CHMA10H3-CHMA11H3",
        "BIOB11H3<BIOB10H3",
        "BIOB12H3<AND-CHMA10H3-CHMA11H3",
        "BIOB33H3<AND-BIOA01H3-BIOA02H3",
        "BIOB34H3<AND-BIOA01H3-BIOA02H3",
        "BIOB34H3<AND-CHMA10H3-CHMA11H3",
        "BIOB50H3<AND-BIOA01H3-BIOA02H3",
        "BIOB51H3<AND-BIOA01H3-BIOA02H3",
        "CHMB41H3<AND-CHMA10H3-CHMA11H3",
        "CHMB42H3<CHMB41H3",
        "BIOC10H3<BIOB11H3",
        "BIOC12H3<BIOB11H3",
        "BIOC12H3<CHMB41H3",
        "BIOC13H3<BIOB11H3",
        "BIOC13H3<CHMB41H3",
        "BIOC14H3<BIOB11H3",
        "BIOC15H3<BIOB11H3",
        "BIOC17H3<BIOB11H3",
        "BIOC19H3<BIOB11H3",
        "BIOC20H3<BIOB11H3",
        "BIOC31H3<BIOB11H3",
        "BIOC35H3<BIOB11H3",
        "BIOC39H3<BIOB11H3",
        "BIOD19H3<BIOC14H3",
        "BIOD20H3<BIOC20H3",
        "BIOD23H3<BIOC12H3",
        "BIOD25H3<BIOC15H3",
        "AND-BIOA01H3-BIOA02H3<BIOA01H3",
        "AND-BIOA01H3-BIOA02H3<BIOA02H3",
        "AND-CHMA10H3-CHMA11H3<CHMA10H3",
        "AND-CHMA10H3-CHMA11H3<CHMA11H3",
        "OR-MATA29H3-MATA30H3-STAB22H3-PSYB07H3<MATA29H3",
        "OR-MATA29H3-MATA30H3-STAB22H3-PSYB07H3<MATA30H3",
        "OR-MATA29H3-MATA30H3-STAB22H3-PSYB07H3<STAB22H3",
        "OR-MATA29H3-MATA30H3-STAB22H3-PSYB07H3<PSYB07H3",
        "OR-BIOB12H3-BIOB32H3-BIOB33H3<BIOB12H3",
        "OR-BIOB12H3-BIOB32H3-BIOB33H3<BIOB32H3",
        "OR-BIOB12H3-BIOB32H3-BIOB33H3<BIOB33H3"
      ],
      "correq":[
        "BIOB12H3<BIOB11H3",
        "BIOB32H3<BIOB34H3"
      ],
      "recommend":[
        "BIOC10H3<BIOC12H3",
        "BIOC12H3<CHMB42H3"
      ],
      "orpre":[
        "BIOC15H3<STAB22H3",
        "BIOC15H3<PSYB07H3",
        "BIOD12H3<BIOC10H3",
        "BIOD12H3<BIOC12H3",
        "BIOD17H3<BIOC17H3",
        "BIOD17H3<BIOC39H3",
        "BIOD26H3<BIOC17H3",
        "BIOD26H3<BIOC39H3",
        "BIOD27H3<BIOB34H3",
        "BIOD29H3<BIOC10H3",
        "BIOD29H3<BIOC20H3",
        "BIOD29H3<BIOC39H3"
      ]
    }
  },
  "mj-hbs":{
    "nodes":{
      "First Year":[
        "BIOA01H3",
        "BIOA02H3",
        "CHMA10H3",
        "CHMA11H3",
        "PSYA01H3",
        "PSYA02H3",
        "MATA29H3",
        "MATA30H3",
        "STAB22H3",
        "PSYB07H3",
        "AND-BIOA01H3-BIOA02H3",
        "AND-CHMA10H3-CHMA11H3",
        "AND-PSYA01H3-PSYA02H3",
        "OR-MATA29H3-MATA30H3-STAB22H3-PSYB07H3",
        "OR-STAB22H3-PSYB07H3",
        "OR-MATA29H3-MATA30H3"
      ],
      "Second Year":[
        "BIOB10H3",
        "BIOB11H3",
        "BIOB34H3",
        "BIOB50H3",
        "BIOB51H3",
        "BIOB32H3",
        "BIOB33H3",
        "NROB60H3",
        "OR-BIOB32H3-BIOB33H3"
      ],
      "Third/Fourth Year":[
        "BIOC10H3",
        "BIOC14H3",
        "BIOC15H3",
        "BIOC16H3",
        "BIOC17H3",
        "BIOC19H3",
        "BIOC20H3",
        "BIOC21H3",
        "BIOC32H3",
        "BIOC34H3",
        "BIOC35H3",
        "BIOC39H3",
        "BIOC54H3",
        "BIOC58H3",
        "BIOC65H3",
        "NROC61H3",
        "NROC64H3",
        "NROC69H3",
        "BIOD07H3",
        "BIOD08H3",
        "BIOD12H3",
        "BIOD17H3",
        "BIOD19H3",
        "BIOD20H3",
        "BIOD26H3",
        "BIOD29H3",
        "BIOD33H3",
        "BIOD35H3",
        "BIOD43H3",
        "BIOD59H3",
        "BIOD65H3",
        "BIOD95H3",
        "NROD66H3",
        "NROD67H3",
        "PSYC08H3",
        "PSYC62H3",
        "NROC34H3"
      ]
    },
    "edges":{
      "andpre":[
        "BIOB10H3<AND-BIOA01H3-BIOA02H3",
        "BIOB10H3<AND-CHMA10H3-CHMA11H3",
        "BIOB11H3<BIOB10H3",
        "BIOB33H3<AND-BIOA01H3-BIOA02H3",
        "BIOB34H3<AND-BIOA01H3-BIOA02H3",
        "BIOB34H3<AND-CHMA10H3-CHMA11H3",
        "BIOB50H3<AND-BIOA01H3-BIOA02H3",
        "BIOB51H3<AND-BIOA01H3-BIOA02H3",
        "NROB60H3<AND-BIOA01H3-BIOA02H3",
        "NROB60H3<AND-PSYA01H3-PSYA02H3",
        "BIOC10H3<BIOB11H3",
        "BIOC14H3<BIOB11H3",
        "BIOC15H3<BIOB11H3",
        "BIOC15H3<OR-STAB22H3-PSYB07H3",
        "BIOC16H3<BIOB51H3",
        "BIOC17H3<BIOB11H3",
        "BIOC19H3<BIOB11H3",
        "BIOC20H3<BIOB11H3",
        "BIOC21H3<BIOB10H3",
        "BIOC21H3<BIOB34H3",
        "BIOC35H3<BIOB11H3",
        "BIOC39H3<BIOB11H3",
        "BIOC54H3<BIOB50H3",
        "BIOC54H3<BIOB51H3",
        "BIOC58H3<BIOB50H3",
        "BIOC58H3<BIOB51H3",
        "BIOC65H3<AND-CHMA10H3-CHMA11H3",
        "BIOC65H3<BIOB50H3",
        "NROC61H3<NROB60H3",
        "NROC64H3<NROB60H3",
        "NROC69H3<NROB60H3",
        "PSYC08H3<OR-STAB22H3-PSYB07H3",
        "PSYC62H3<OR-STAB22H3-PSYB07H3",
        "BIOD08H3<OR-STAB22H3-PSYB07H3",
        "BIOD08H3<OR-MATA29H3-MATA30H3",
        "BIOD19H3<BIOC14H3",
        "BIOD20H3<BIOC20H3",
        "BIOD33H3<BIOC34H3",
        "BIOD35H3<BIOC34H3",
        "BIOD43H3<BIOC34H3",
        "BIOD59H3<BIOB50H3",
        "BIOD59H3<OR-MATA29H3-MATA30H3",
        "BIOD65H3<BIOB11H3",
        "NROD66H3<PSYC62H3",
        "NROD67H3<NROB60H3",
        "AND-BIOA01H3-BIOA02H3<BIOA01H3",
        "AND-BIOA01H3-BIOA02H3<BIOA02H3",
        "AND-CHMA10H3-CHMA11H3<CHMA10H3",
        "AND-CHMA10H3-CHMA11H3<CHMA11H3",
        "AND-PSYA01H3-PSYA02H3<PSYA01H3",
        "AND-PSYA01H3-PSYA02H3<PSYA02H3",
        "OR-MATA29H3-MATA30H3-STAB22H3-PSYB07H3<MATA29H3",
        "OR-MATA29H3-MATA30H3-STAB22H3-PSYB07H3<MATA30H3",
        "OR-MATA29H3-MATA30H3-STAB22H3-PSYB07H3<STAB22H3",
        "OR-MATA29H3-MATA30H3-STAB22H3-PSYB07H3<PSYB07H3",
        "OR-BIOB32H3-BIOB33H3<BIOB32H3",
        "OR-BIOB32H3-BIOB33H3<BIOB33H3",
        "OR-STAB22H3-PSYB07H3<STAB22H3",
        "OR-STAB22H3-PSYB07H3<PSYB07H3",
        "OR-MATA29H3-MATA30H3<MATA29H3",
        "OR-MATA29H3-MATA30H3<MATA30H3"
      ],
      "correq":[
        "BIOB32H3<BIOB34H3"
      ],
      "recommend":[
        "BIOC16H3<BIOC15H3",
        "NROD66H3<PSYC08H3"
      ],
      "orpre":[
        "BIOC32H3<NROB60H3",
        "BIOC32H3<BIOB34H3",
        "BIOC34H3<NROB60H3",
        "BIOC34H3<BIOB34H3",
        "NROC34H3<NROB60H3",
        "NROC34H3<BIOB34H3",
        "BIOD07H3<BIOC32H3",
        "BIOD07H3<NROC34H3",
        "BIOD07H3<NROC64H3",
        "BIOD07H3<NROC69H3",
        "BIOD08H3<NROC34H3",
        "BIOD08H3<NROC64H3",
        "BIOD08H3<NROC69H3",
        "BIOD12H3<BIOC10H3",
        "BIOD17H3<BIOC17H3",
        "BIOD17H3<BIOC39H3",
        "BIOD26H3<BIOC17H3",
        "BIOD26H3<BIOC39H3",
        "BIOD29H3<BIOC10H3",
        "BIOD29H3<BIOC20H3",
        "BIOD29H3<BIOC39H3",
        "BIOD65H3<BIOC32H3",
        "BIOD65H3<NROC61H3",
        "BIOD65H3<NROC64H3",
        "BIOD65H3<NROC69H3",
        "NROD66H3<NROC61H3",
        "NROD66H3<NROC64H3",
        "NROD67H3<NROC61H3",
        "NROD67H3<NROC64H3"
      ]
    }
  },
  "mj-cbs":{
    "nodes":{
      "First Year":[
        "BIOA01H3",
        "BIOA02H3",
        "CHMA10H3",
        "CHMA11H3",
        "MATA29H3",
        "MATA30H3",
        "STAB22H3",
        "PSYB07H3",
        "AND-BIOA01H3-BIOA02H3",
        "AND-CHMA10H3-CHMA11H3",
        "OR-MATA29H3-MATA30H3-STAB22H3-PSYB07H3",
        "PHYA10H3",
        "PHYA11H3",
        "OR-PHYA10H3-PHYA11H3"
      ],
      "Second Year":[
        "BIOB10H3",
        "BIOB11H3",
        "BIOB34H3",
        "BIOB38H3",
        "BIOB50H3",
        "BIOB51H3",
        "BIOB52H3",
        "NROB60H3"
      ],
      "Third Year":[
        "BIOC16H3",
        "BIOC50H3",
        "BIOC59H3",
        "BIOC61H3",
        "BIOC37H3",
        "BIOC40H3",
        "BIOC51H3",
        "BIOC52H3",
        "BIOC54H3",
        "BIOC58H3",
        "BIOC60H3",
        "BIOC62H3",
        "BIOC63H3",
        "BIOC65H3",
        "EESC04H3",
        "EESC30H3",
        "BIOC15H3",
        "BIOC17H3",
        "BIOC39H3",
        "BIOC34H3",
        "NROC34H3"
      ],
      "Fourth Year":[
        "BIOD25H3",
        "BIOD26H3",
        "BIOD33H3",
        "BIOD43H3",
        "BIOD45H3",
        "BIOD48H3",
        "BIOD52H3",
        "BIOD53H3",
        "BIOD54H3",
        "BIOD55H3",
        "BIOD59H3",
        "BIOD60H3",
        "BIOD62H3",
        "BIOD63H3",
        "BIOD66H3",
        "BIOD67H3",
        "EESD15H3"
      ]
    },
    "edges":{
      "andpre":[
        "BIOB10H3<AND-BIOA01H3-BIOA02H3",
        "BIOB10H3<AND-CHMA10H3-CHMA11H3",
        "BIOB11H3<BIOB10H3",
        "BIOB34H3<AND-BIOA01H3-BIOA02H3",
        "BIOB34H3<AND-CHMA10H3-CHMA11H3",
        "BIOB38H3<AND-BIOA01H3-BIOA02H3",
        "BIOB50H3<AND-BIOA01H3-BIOA02H3",
        "BIOB51H3<AND-BIOA01H3-BIOA02H3",
        "BIOB52H3<AND-BIOA01H3-BIOA02H3",
        "BIOC15H3<BIOB11H3",
        "BIOC16H3<BIOB51H3",
        "BIOC17H3<BIOB11H3",
        "BIOC39H3<BIOB11H3",
        "BIOC40H3<BIOB11H3",
        "BIOC50H3<BIOB50H3",
        "BIOC50H3<BIOB51H3",
        "BIOC51H3<BIOB50H3",
        "BIOC51H3<BIOB51H3",
        "BIOC51H3<BIOB52H3",
        "BIOC54H3<BIOB50H3",
        "BIOC54H3<BIOB51H3",
        "BIOC58H3<BIOB50H3",
        "BIOC58H3<BIOB51H3",
        "BIOC59H3<BIOB50H3",
        "BIOC61H3<BIOB50H3",
        "BIOC62H3<BIOB50H3",
        "BIOC62H3<BIOB51H3",
        "BIOC63H3<BIOB50H3",
        "BIOC63H3<BIOB51H3",
        "BIOC65H3<AND-CHMA10H3-CHMA11H3",
        "BIOC65H3<BIOB50H3",
        "EESC04H3<BIOB50H3",
        "EESC30H3<BIOB50H3",
        "EESC30H3<BIOB51H3",
        "EESC30H3<AND-CHMA10H3-CHMA11H3",
        "BIOD25H3<BIOC15H3",
        "BIOD33H3<BIOC34H3",
        "BIOD43H3<BIOC34H3",
        "BIOD48H3<BIOB50H3",
        "BIOD48H3<BIOB51H3",
        "BIOD53H3<BIOC54H3",
        "BIOD55H3<BIOC54H3",
        "BIOD59H3<BIOB50H3",
        "BIOD60H3<BIOB50H3",
        "BIOD60H3<STAB22H3",
        "BIOD63H3<BIOB50H3",
        "BIOD63H3<BIOB51H3",
        "BIOD66H3<BIOB51H3",
        "EESD15H3<AND-CHMA10H3-CHMA11H3",
        "EESD15H3<AND-BIOA01H3-BIOA02H3",
        "EESD15H3<OR-PHYA10H3-PHYA11H3",
        "AND-BIOA01H3-BIOA02H3<BIOA01H3",
        "AND-BIOA01H3-BIOA02H3<BIOA02H3",
        "AND-CHMA10H3-CHMA11H3<CHMA10H3",
        "AND-CHMA10H3-CHMA11H3<CHMA11H3",
        "OR-MATA29H3-MATA30H3-STAB22H3-PSYB07H3<MATA29H3",
        "OR-MATA29H3-MATA30H3-STAB22H3-PSYB07H3<MATA30H3",
        "OR-MATA29H3-MATA30H3-STAB22H3-PSYB07H3<STAB22H3",
        "OR-MATA29H3-MATA30H3-STAB22H3-PSYB07H3<PSYB07H3",
        "OR-PHYA10H3-PHYA11H3<PHYA10H3",
        "OR-PHYA10H3-PHYA11H3<PHYA11H3"
      ],
      "correq":[
        "BIOB52H3<BIOB50H3",
        "BIOB52H3<BIOB51H3",
        "BIOC52H3<BIOB50H3",
        "BIOC52H3<BIOB51H3"
      ],
      "recommend":[

      ],
      "orpre":[
        "BIOC15H3<STAB22H3",
        "BIOC15H3<PSYB07H3",
        "BIOC34H3<BIOB34H3",
        "BIOC34H3<NROB60H3",
        "BIOC37H3<BIOB38H3",
        "BIOC37H3<BIOB50H3",
        "BIOC37H3<BIOB51H3",
        "BIOC60H3<BIOB50H3",
        "BIOC60H3<BIOB51H3",
        "NROC34H3<NROB60H3",
        "NROC34H3<BIOB34H3",
        "BIOD26H3<BIOC17H3",
        "BIOD26H3<BIOC39H3",
        "BIOD45H3<BIOC54H3",
        "BIOD45H3<NROC34H3",
        "BIOD48H3<BIOC50H3",
        "BIOD48H3<BIOC54H3",
        "BIOD48H3<BIOC61H3",
        "BIOD52H3<BIOC50H3",
        "BIOD52H3<BIOC63H3",
        "BIOD54H3<BIOC62H3",
        "BIOD54H3<BIOC63H3",
        "BIOD59H3<MATA29H3",
        "BIOD59H3<MATA30H3",
        "BIOD60H3<BIOC59H3",
        "BIOD60H3<BIOC61H3",
        "BIOD62H3<BIOC16H3",
        "BIOD62H3<BIOC50H3",
        "BIOD63H3<BIOC51H3",
        "BIOD63H3<BIOC52H3",
        "BIOD63H3<BIOC54H3",
        "BIOD63H3<BIOC58H3",
        "BIOD63H3<BIOC59H3",
        "BIOD63H3<BIOC60H3",
        "BIOD63H3<BIOC61H3",
        "BIOD66H3<BIOC59H3",
        "BIOD66H3<BIOC61H3"
      ]
    }
  },
  "mj-bs":{
    "nodes":{
      "First Year":[
        "BIOA01H3",
        "BIOA02H3",
        "CHMA10H3",
        "CHMA11H3",
        "MATA29H3",
        "MATA30H3",
        "STAB22H3",
        "PSYB07H3",
        "AND-BIOA01H3-BIOA02H3",
        "AND-CHMA10H3-CHMA11H3",
        "OR-MATA29H3-MATA30H3-STAB22H3-PSYB07H3"
      ],
      "Second Year":[
        "BIOB10H3",
        "BIOB11H3",
        "BIOB34H3",
        "BIOB38H3",
        "BIOB50H3",
        "BIOB51H3",
        "BIOB12H3",
        "BIOB32H3",
        "BIOB33H3",
        "BIOB52H3"
      ]
    },
    "edges":{
      "andpre":[
        "BIOB10H3<AND-BIOA01H3-BIOA02H3",
        "BIOB10H3<AND-CHMA10H3-CHMA11H3",
        "BIOB11H3<BIOB10H3",
        "BIOB12H3<AND-CHMA10H3-CHMA11H3",
        "BIOB33H3<AND-BIOA01H3-BIOA02H3",
        "BIOB34H3<AND-BIOA01H3-BIOA02H3",
        "BIOB34H3<AND-CHMA10H3-CHMA11H3",
        "BIOB38H3<AND-BIOA01H3-BIOA02H3",
        "BIOB50H3<AND-BIOA01H3-BIOA02H3",
        "BIOB51H3<AND-BIOA01H3-BIOA02H3",
        "BIOB52H3<AND-BIOA01H3-BIOA02H3",
        "AND-BIOA01H3-BIOA02H3<BIOA01H3",
        "AND-BIOA01H3-BIOA02H3<BIOA02H3",
        "AND-CHMA10H3-CHMA11H3<CHMA10H3",
        "AND-CHMA10H3-CHMA11H3<CHMA11H3",
        "OR-MATA29H3-MATA30H3-STAB22H3-PSYB07H3<MATA29H3",
        "OR-MATA29H3-MATA30H3-STAB22H3-PSYB07H3<MATA30H3",
        "OR-MATA29H3-MATA30H3-STAB22H3-PSYB07H3<STAB22H3",
        "OR-MATA29H3-MATA30H3-STAB22H3-PSYB07H3<PSYB07H3"
      ],
      "correq":[
        "BIOB12H3<BIOB11H3",
        "BIOB32H3<BIOB34H3"
      ],
      "recommend":[

      ],
      "orpre":[

      ]
    }
  },
  "sp-combbs":{
    "nodes":{
      "First Year":[
        "BIOA01H3",
        "BIOA02H3",
        "CHMA10H3",
        "CHMA11H3",
        "MATA29H3",
        "MATA35H3",
        "MATA30H3",
        "MATA36H3",
        "PHYA10H3",
        "PHYA11H3",
        "PHYA21H3",
        "PHYA22H3",
        "STAB22H3",
        "PSYB07H3",
        "AND-BIOA01H3-BIOA02H3",
        "AND-CHMA10H3-CHMA11H3",
        "AND-MATA29,35",
        "AND-MATA30,36",
        "OR-MA1-MA2",
        "OR-PHYA10,11",
        "OR-PHYA21,22",
        "AND-P1-P2"
      ],
      "Second Year":[
        "BIOB10H3",
        "BIOB11H3",
        "BIOB34H3",
        "BIOB38H3",
        "BIOB50H3",
        "BIOB51H3",
        "BIOB12H3",
        "CHMB41H3",
        "CHMB42H3",
        "OR-STAB22H3-PSYB07H3"
      ],
      "Third Year":[
        "BIOC12H3",
        "BIOC13H3",
        "BIOC15H3",
        "BIOC17H3",
        "BIOC20H3",
        "BIOC23H3",
        "BIOC39H3",
        "CSCA08H3",
        "CSCA20H3",
        "PSCB57H3",
        "OR-CSCA08H3-CSCA20H3-PSCB57H3",
        "BIOC32H3",
        "BIOC34H3",
        "BIOC37H3"
      ],
      "Third/Fourth Year":[
        "BIOC10H3",
        "BIOC14H3",
        "BIOC19H3",
        "BIOC21H3",
        "BIOC31H3",
        "BIOC35H3",
        "BIOC40H3",
        "BIOD37H3"
      ],
      "Fourth Year":[
        "BIOD21H3",
        "BIOD12H3",
        "BIOD17H3",
        "BIOD19H3",
        "BIOD20H3",
        "BIOD22H3",
        "BIOD23H3",
        "BIOD25H3",
        "BIOD26H3",
        "BIOD27H3",
        "BIOD29H3",
        "BIOD30H3"
      ]
    },
    "edges":{
      "andpre":[
        "BIOB10H3<AND-BIOA01H3-BIOA02H3",
        "BIOB10H3<AND-CHMA10H3-CHMA11H3",
        "BIOB11H3<BIOB10H3",
        "BIOB12H3<AND-CHMA10H3-CHMA11H3",
        "BIOB34H3<AND-BIOA01H3-BIOA02H3",
        "BIOB34H3<AND-CHMA10H3-CHMA11H3",
        "BIOB38H3<AND-BIOA01H3-BIOA02H3",
        "BIOB50H3<AND-BIOA01H3-BIOA02H3",
        "BIOB51H3<AND-BIOA01H3-BIOA02H3",
        "CHMB41H3<AND-CHMA10H3-CHMA11H3",
        "CHMB42H3<CHMB41H3",
        "BIOC10H3<BIOB11H3",
        "BIOC12H3<BIOB11H3",
        "BIOC12H3<CHMB41H3",
        "BIOC13H3<BIOB11H3",
        "BIOC13H3<CHMB41H3",
        "BIOC14H3<BIOB11H3",
        "BIOC15H3<BIOB11H3",
        "BIOC15H3<OR-STAB22H3-PSYB07H3",
        "BIOC17H3<BIOB11H3",
        "BIOC19H3<BIOB11H3",
        "BIOC20H3<BIOB11H3",
        "BIOC21H3<BIOB10H3",
        "BIOC21H3<BIOB34H3",
        "BIOC23H3<BIOB12H3",
        "BIOC23H3<BIOC12H3",
        "BIOC31H3<BIOB11H3",
        "BIOC35H3<BIOB11H3",
        "BIOC39H3<BIOB11H3",
        "BIOC40H3<BIOB11H3",
        "BIOD19H3<BIOC14H3",
        "BIOD20H3<BIOC20H3",
        "BIOD21H3<BIOB12H3",
        "BIOD21H3<BIOC15H3",
        "BIOD21H3<BIOC17H3",
        "BIOD23H3<BIOC12H3",
        "BIOD25H3<BIOC15H3",
        "BIOD30H3<BIOB38H3",
        "BIOD37H3<BIOB11H3",
        "AND-BIOA01H3-BIOA02H3<BIOA01H3",
        "AND-BIOA01H3-BIOA02H3<BIOA02H3",
        "AND-CHMA10H3-CHMA11H3<CHMA10H3",
        "AND-CHMA10H3-CHMA11H3<CHMA11H3",
        "OR-STAB22H3-PSYB07H3<STAB22H3",
        "OR-STAB22H3-PSYB07H3<PSYB07H3",
        "AND-MATA29,35<MATA29H3",
        "AND-MATA29,35<MATA35H3",
        "AND-MATA30,36<MATA30H3",
        "AND-MATA30,36<MATA36H3",
        "OR-MA1-MA2<AND-MATA29,35",
        "OR-MA1-MA2<AND-MATA30,36",
        "OR-PHYA10,11<PHYA10H3",
        "OR-PHYA10,11<PHYA11H3",
        "OR-PHYA21,22<PHYA21H3",
        "OR-PHYA21,22<PHYA22H3",
        "AND-P1-P2<OR-PHYA10,11",
        "AND-P1-P2<OR-PHYA21,22",
        "OR-CSCA08H3-CSCA20H3-PSCB57H3<CSCA08H3",
        "OR-CSCA08H3-CSCA20H3-PSCB57H3<CSCA20H3",
        "OR-CSCA08H3-CSCA20H3-PSCB57H3<PSCB57H3"
      ],
      "correq":[
        "BIOB12H3<BIOB11H3",
        "BIOD21H3<BIOC12H3"
      ],
      "recommend":[
        "BIOB34H3<MATA29H3",
        "BIOC10H3<BIOC12H3",
        "BIOC12H3<CHMB42H3",
        "BIOD27H3<BIOC34H3"
      ],
      "orpre":[
        "BIOC32H3<BIOB34H3",
        "BIOC34H3<BIOB34H3",
        "BIOC37H3<BIOB38H3",
        "BIOC37H3<BIOB50H3",
        "BIOC37H3<BIOB51H3",
        "BIOD12H3<BIOC10H3",
        "BIOD12H3<BIOC12H3",
        "BIOD17H3<BIOC17H3",
        "BIOD17H3<BIOC39H3",
        "BIOD22H3<BIOC10H3",
        "BIOD22H3<BIOC12H3",
        "BIOD22H3<BIOC15H3",
        "BIOD26H3<BIOC17H3",
        "BIOD26H3<BIOC39H3",
        "BIOD27H3<BIOB34H3",
        "BIOD27H3<BIOC32H3",
        "BIOD29H3<BIOC10H3",
        "BIOD29H3<BIOC20H3",
        "BIOD29H3<BIOC39H3",
        "BIOD30H3<BIOC15H3",
        "BIOD30H3<BIOC31H3",
        "BIOD30H3<BIOC37H3",
        "BIOD30H3<BIOC40H3",
        "BIOD37H3<BIOC31H3",
        "BIOD37H3<BIOC40H3"
      ]
    }
  },
  "sp-mbbs":{
    "nodes":{
      "First Year":[
        "BIOA01H3",
        "BIOA02H3",
        "CHMA10H3",
        "CHMA11H3",
        "MATA29H3",
        "MATA35H3",
        "MATA30H3",
        "MATA36H3",
        "PHYA10H3",
        "PHYA11H3",
        "PHYA21H3",
        "PHYA22H3",
        "STAB22H3",
        "PSYB07H3",
        "AND-BIOA01H3-BIOA02H3",
        "AND-CHMA10H3-CHMA11H3",
        "OR-STAB22H3-PSYB07H3",
        "AND-MATA29,35",
        "AND-MATA30,36",
        "OR-MA1-MA2",
        "OR-PHYA10,11",
        "OR-PHYA21,22",
        "AND-P1-P2"
      ],
      "Second Year":[
        "BIOB10H3",
        "BIOB11H3",
        "BIOB34H3",
        "BIOB38H3",
        "BIOB50H3",
        "BIOB51H3",
        "BIOB12H3",
        "CHMB41H3",
        "CHMB42H3"
      ],
      "Third Year":[
        "BIOC12H3",
        "BIOC13H3",
        "BIOC15H3",
        "BIOC17H3",
        "BIOC20H3",
        "BIOC23H3",
        "BIOC39H3",
        "CSCA08H3",
        "CSCA20H3",
        "PSCB57H3",
        "OR-CSCA08H3-CSCA20H3-PSCB57H3",
        "BIOC32H3",
        "BIOC34H3",
        "BIOC37H3"
      ],
      "Third/Fourth Year":[
        "BIOC10H3",
        "BIOC14H3",
        "BIOC19H3",
        "BIOC21H3",
        "BIOC31H3",
        "BIOC35H3",
        "BIOC40H3",
        "BIOD37H3"
      ],
      "Fourth Year":[
        "BIOD21H3",
        "BIOD12H3",
        "BIOD17H3",
        "BIOD19H3",
        "BIOD20H3",
        "BIOD22H3",
        "BIOD23H3",
        "BIOD25H3",
        "BIOD26H3",
        "BIOD27H3",
        "BIOD29H3",
        "BIOD30H3"
      ]
    },
    "edges":{
      "andpre":[
        "BIOB10H3<AND-BIOA01H3-BIOA02H3",
        "BIOB10H3<AND-CHMA10H3-CHMA11H3",
        "BIOB11H3<BIOB10H3",
        "BIOB12H3<AND-CHMA10H3-CHMA11H3",
        "BIOB34H3<AND-BIOA01H3-BIOA02H3",
        "BIOB34H3<AND-CHMA10H3-CHMA11H3",
        "BIOB38H3<AND-BIOA01H3-BIOA02H3",
        "BIOB50H3<AND-BIOA01H3-BIOA02H3",
        "BIOB51H3<AND-BIOA01H3-BIOA02H3",
        "CHMB41H3<AND-CHMA10H3-CHMA11H3",
        "CHMB42H3<CHMB41H3",
        "BIOC10H3<BIOB11H3",
        "BIOC12H3<BIOB11H3",
        "BIOC12H3<CHMB41H3",
        "BIOC13H3<BIOB11H3",
        "BIOC13H3<CHMB41H3",
        "BIOC14H3<BIOB11H3",
        "BIOC15H3<BIOB11H3",
        "BIOC15H3<OR-STAB22H3-PSYB07H3",
        "BIOC17H3<BIOB11H3",
        "BIOC19H3<BIOB11H3",
        "BIOC20H3<BIOB11H3",
        "BIOC21H3<BIOB10H3",
        "BIOC21H3<BIOB34H3",
        "BIOC23H3<BIOB12H3",
        "BIOC23H3<BIOC12H3",
        "BIOC31H3<BIOB11H3",
        "BIOC35H3<BIOB11H3",
        "BIOC39H3<BIOB11H3",
        "BIOC40H3<BIOB11H3",
        "BIOD19H3<BIOC14H3",
        "BIOD20H3<BIOC20H3",
        "BIOD21H3<BIOB12H3",
        "BIOD21H3<BIOC15H3",
        "BIOD21H3<BIOC17H3",
        "BIOD23H3<BIOC12H3",
        "BIOD25H3<BIOC15H3",
        "BIOD30H3<BIOB38H3",
        "BIOD37H3<BIOB11H3",
        "AND-BIOA01H3-BIOA02H3<BIOA01H3",
        "AND-BIOA01H3-BIOA02H3<BIOA02H3",
        "AND-CHMA10H3-CHMA11H3<CHMA10H3",
        "AND-CHMA10H3-CHMA11H3<CHMA11H3",
        "OR-STAB22H3-PSYB07H3<STAB22H3",
        "OR-STAB22H3-PSYB07H3<PSYB07H3",
        "AND-MATA29,35<MATA29H3",
        "AND-MATA29,35<MATA35H3",
        "AND-MATA30,36<MATA30H3",
        "AND-MATA30,36<MATA36H3",
        "OR-MA1-MA2<AND-MATA29,35",
        "OR-MA1-MA2<AND-MATA30,36",
        "OR-PHYA10,11<PHYA10H3",
        "OR-PHYA10,11<PHYA11H3",
        "OR-PHYA21,22<PHYA21H3",
        "OR-PHYA21,22<PHYA22H3",
        "AND-P1-P2<OR-PHYA10,11",
        "AND-P1-P2<OR-PHYA21,22",
        "OR-CSCA08H3-CSCA20H3-PSCB57H3<CSCA08H3",
        "OR-CSCA08H3-CSCA20H3-PSCB57H3<CSCA20H3",
        "OR-CSCA08H3-CSCA20H3-PSCB57H3<PSCB57H3"
      ],
      "correq":[
        "BIOB12H3<BIOB11H3",
        "BIOD21H3<BIOC12H3"
      ],
      "recommend":[
        "BIOB34H3<MATA29H3",
        "BIOC10H3<BIOC12H3",
        "BIOC12H3<CHMB42H3",
        "BIOD27H3<BIOC34H3"
      ],
      "orpre":[
        "BIOC32H3<BIOB34H3",
        "BIOC34H3<BIOB34H3",
        "BIOC37H3<BIOB38H3",
        "BIOC37H3<BIOB50H3",
        "BIOC37H3<BIOB51H3",
        "BIOD12H3<BIOC10H3",
        "BIOD12H3<BIOC12H3",
        "BIOD17H3<BIOC17H3",
        "BIOD17H3<BIOC39H3",
        "BIOD22H3<BIOC10H3",
        "BIOD22H3<BIOC12H3",
        "BIOD22H3<BIOC15H3",
        "BIOD26H3<BIOC17H3",
        "BIOD26H3<BIOC39H3",
        "BIOD27H3<BIOB34H3",
        "BIOD27H3<BIOC32H3",
        "BIOD29H3<BIOC10H3",
        "BIOD29H3<BIOC20H3",
        "BIOD29H3<BIOC39H3",
        "BIOD30H3<BIOC15H3",
        "BIOD30H3<BIOC31H3",
        "BIOD30H3<BIOC37H3",
        "BIOD30H3<BIOC40H3",
        "BIOD37H3<BIOC31H3",
        "BIOD37H3<BIOC40H3"
      ]
    }
  },
  "sp-hbs":{
    "nodes":{
      "First Year":[
        "BIOA01H3",
        "BIOA02H3",
        "CHMA10H3",
        "CHMA11H3",
        "MATA29H3",
        "MATA35H3",
        "MATA30H3",
        "MATA36H3",
        "PHYA11H3",
        "PHYA22H3",
        "STAB22H3",
        "PSYB07H3",
        "HLTA02H3",
        "HLTA03H3",
        "HLTB15H3",
        "HLTB16H3",
        "HLTB20H3",
        "HLTB22H3",
        "HLTB40H3",
        "PSYA01H3",
        "PSYA02H3",
        "AND-BIOA01H3-BIOA02H3",
        "AND-CHMA10H3-CHMA11H3",
        "OR-STAB22H3-PSYB07H3",
        "AND-MATA29,35",
        "AND-MATA30,36",
        "OR-MA1-MA2",
        "AND-PHYA11H3-PHYA22H3",
        "OR-HL"
      ],
      "Second Year":[
        "BIOB10H3",
        "BIOB11H3",
        "BIOB34H3",
        "BIOB38H3",
        "BIOB50H3",
        "BIOB51H3",
        "BIOB32H3",
        "BIOB33H3",
        "CHMB41H3",
        "CHMB42H3",
        "NROB60H3"
      ],
      "Third/Fourth Year":[
        "BIOC15H3",
        "BIOC17H3",
        "BIOC20H3",
        "BIOC32H3",
        "BIOC34H3",
        "BIOC39H3",
        "BIOC10H3",
        "BIOC12H3",
        "BIOC13H3",
        "BIOC14H3",
        "BIOC16H3",
        "BIOC19H3",
        "BIOC21H3",
        "BIOC35H3",
        "BIOC40H3",
        "BIOC58H3",
        "BIOC65H3",
        "BIOD12H3",
        "BIOD17H3",
        "BIOD19H3",
        "BIOD20H3",
        "BIOD26H3",
        "BIOD27H3",
        "BIOD29H3",
        "BIOD33H3",
        "BIOD35H3",
        "BIOD37H3",
        "BIOD43H3",
        "BIOD59H3",
        "BIOD65H3"
      ]
    },
    "edges":{
      "andpre":[
        "BIOB10H3<AND-BIOA01H3-BIOA02H3",
        "BIOB10H3<AND-CHMA10H3-CHMA11H3",
        "BIOB11H3<BIOB10H3",
        "BIOB33H3<AND-BIOA01H3-BIOA02H3",
        "BIOB34H3<AND-BIOA01H3-BIOA02H3",
        "BIOB34H3<AND-CHMA10H3-CHMA11H3",
        "BIOB38H3<AND-BIOA01H3-BIOA02H3",
        "BIOB50H3<AND-BIOA01H3-BIOA02H3",
        "BIOB51H3<AND-BIOA01H3-BIOA02H3",
        "CHMB41H3<AND-CHMA10H3-CHMA11H3",
        "CHMB42H3<AND-CHMA10H3-CHMA11H3",
        "CHMB42H3<CHMB41H3",
        "NROB60H3<AND-BIOA01H3-BIOA02H3",
        "NROB60H3<PSYA01H3",
        "NROB60H3<PSYA02H3",
        "BIOC10H3<BIOB11H3",
        "BIOC12H3<BIOB11H3",
        "BIOC12H3<CHMB41H3",
        "BIOC13H3<BIOB11H3",
        "BIOC13H3<CHMB41H3",
        "BIOC14H3<BIOB11H3",
        "BIOC15H3<BIOB11H3",
        "BIOC15H3<OR-STAB22H3-PSYB07H3",
        "BIOC16H3<BIOB51H3",
        "BIOC17H3<BIOB11H3",
        "BIOC19H3<BIOB11H3",
        "BIOC20H3<BIOB11H3",
        "BIOC21H3<BIOB10H3",
        "BIOC21H3<BIOB34H3",
        "BIOC35H3<BIOB11H3",
        "BIOC39H3<BIOB11H3",
        "BIOC40H3<BIOB11H3",
        "BIOC58H3<BIOB50H3",
        "BIOC58H3<BIOB51H3",
        "BIOC65H3<AND-CHMA10H3-CHMA11H3",
        "BIOC65H3<BIOB50H3",
        "BIOD19H3<BIOC14H3",
        "BIOD20H3<BIOC20H3",
        "BIOD33H3<BIOC34H3",
        "BIOD35H3<BIOC34H3",
        "BIOD37H3<BIOB11H3",
        "BIOD43H3<BIOC34H3",
        "BIOD59H3<BIOB50H3",
        "BIOD65H3<BIOB11H3",
        "AND-BIOA01H3-BIOA02H3<BIOA01H3",
        "AND-BIOA01H3-BIOA02H3<BIOA02H3",
        "AND-CHMA10H3-CHMA11H3<CHMA10H3",
        "AND-CHMA10H3-CHMA11H3<CHMA11H3",
        "OR-STAB22H3-PSYB07H3<STAB22H3",
        "OR-STAB22H3-PSYB07H3<PSYB07H3",
        "AND-MATA29,35<MATA29H3",
        "AND-MATA29,35<MATA35H3",
        "AND-MATA30,36<MATA30H3",
        "AND-MATA30,36<MATA36H3",
        "OR-MA1-MA2<AND-MATA29,35",
        "OR-MA1-MA2<AND-MATA30,36",
        "AND-PHYA11H3-PHYA22H3<PHYA11H3",
        "AND-PHYA11H3-PHYA22H3<PHYA22H3",
        "OR-HL<HLTA02H3",
        "OR-HL<HLTA03H3",
        "OR-HL<HLTB15H3",
        "OR-HL<HLTB16H3",
        "OR-HL<HLTB20H3",
        "OR-HL<HLTB22H3",
        "OR-HL<HLTB40H3",
        "OR-HL<PSYA01H3",
        "OR-HL<PSYA02H3"
      ],
      "correq":[
        "BIOB32H3<BIOB34H3"
      ],
      "recommend":[
        "BIOB34H3<MATA29H3",
        "BIOC10H3<BIOC12H3",
        "BIOC12H3<CHMB42H3",
        "BIOC16H3<BIOC15H3",
        "BIOD27H3<BIOC34H3"
      ],
      "orpre":[
        "BIOC32H3<NROB60H3",
        "BIOC32H3<BIOB34H3",
        "BIOC34H3<NROB60H3",
        "BIOC34H3<BIOB34H3",
        "BIOD12H3<BIOC10H3",
        "BIOD12H3<BIOC12H3",
        "BIOD17H3<BIOC17H3",
        "BIOD17H3<BIOC39H3",
        "BIOD26H3<BIOC17H3",
        "BIOD26H3<BIOC39H3",
        "BIOD27H3<BIOB34H3",
        "BIOD27H3<BIOC32H3",
        "BIOD29H3<BIOC10H3",
        "BIOD29H3<BIOC20H3",
        "BIOD29H3<BIOC39H3",
        "BIOD37H3<BIOC40H3",
        "BIOD59H3<MATA29H3",
        "BIOD59H3<MATA30H3",
        "BIOD65H3<BIOC32H3"
      ]
    }
  },
  "sp-cbs":{
    "nodes":{
      "First Year":[
        "BIOA01H3",
        "BIOA02H3",
        "CHMA10H3",
        "CHMA11H3",
        "MATA29H3",
        "MATA35H3",
        "MATA30H3",
        "MATA36H3",
        "PHYA10H3",
        "PHYA11H3",
        "CSCA08H3",
        "CSCA20H3",
        "PSCB57H3",
        "AND-BIOA01H3-BIOA02H3",
        "AND-CHMA10H3-CHMA11H3",
        "AND-MATA29,35",
        "AND-MATA30,36",
        "OR-MA1-MA2",
        "OR-PHYA10H3-PHYA11H3",
        "OR-CSCA08H3-CSCA20H3-PSCB57H3"
      ],
      "Second Year":[
        "BIOB10H3",
        "BIOB11H3",
        "BIOB34H3",
        "BIOB38H3",
        "BIOB50H3",
        "BIOB51H3",
        "BIOB52H3",
        "STAB22H3",
        "PSYB07H3",
        "OR-STAB22H3-PSYB07H3",
        "NROB60H3"
      ],
      "Third Year":[
        "BIOC16H3",
        "BIOC50H3",
        "BIOC59H3",
        "BIOC61H3"
      ],
      "Ecology and Evolution":[
        "BIOC51H3",
        "BIOC52H3",
        "BIOC58H3",
        "BIOC60H3",
        "BIOC63H3",
        "BIOC65H3",
        "BIOD25H3",
        "BIOD52H3",
        "BIOD54H3",
        "BIOD55H3",
        "BIOD59H3",
        "BIOD60H3",
        "BIOD62H3",
        "BIOD63H3",
        "BIOD66H3",
        "BIOD67H3",
        "EESC04H3",
        "BIOC15H3"
      ],
      "Organismal Biology":[
        "BIOC37H3",
        "BIOC40H3",
        "BIOC54H3",
        "BIOC62H3",
        "BIOD26H3",
        "BIOD33H3",
        "BIOD37H3",
        "BIOD43H3",
        "BIOD45H3",
        "BIOD48H3",
        "BIOD53H3",
        "EESC30H3",
        "NROC34H3",
        "BIOC34H3",
        "BIOC17H3",
        "BIOC39H3",
        "BIOC31H3"
      ]
    },
    "edges":{
      "andpre":[
        "BIOB10H3<AND-BIOA01H3-BIOA02H3",
        "BIOB10H3<AND-CHMA10H3-CHMA11H3",
        "BIOB11H3<BIOB10H3",
        "BIOB34H3<AND-BIOA01H3-BIOA02H3",
        "BIOB34H3<AND-CHMA10H3-CHMA11H3",
        "BIOB38H3<AND-BIOA01H3-BIOA02H3",
        "BIOB50H3<AND-BIOA01H3-BIOA02H3",
        "BIOB51H3<AND-BIOA01H3-BIOA02H3",
        "BIOB52H3<AND-BIOA01H3-BIOA02H3",
        "BIOC15H3<BIOB11H3",
        "BIOC15H3<OR-STAB22H3-PSYB07H3",
        "BIOC16H3<BIOB51H3",
        "BIOC17H3<BIOB11H3",
        "BIOC31H3<BIOB11H3",
        "BIOC39H3<BIOB11H3",
        "BIOC40H3<BIOB11H3",
        "BIOC50H3<BIOB50H3",
        "BIOC50H3<BIOB51H3",
        "BIOC51H3<BIOB50H3",
        "BIOC51H3<BIOB51H3",
        "BIOC51H3<BIOB52H3",
        "BIOC54H3<BIOB50H3",
        "BIOC54H3<BIOB51H3",
        "BIOC58H3<BIOB50H3",
        "BIOC58H3<BIOB51H3",
        "BIOC59H3<BIOB50H3",
        "BIOC61H3<BIOB50H3",
        "BIOC62H3<BIOB50H3",
        "BIOC62H3<BIOB51H3",
        "BIOC63H3<BIOB50H3",
        "BIOC63H3<BIOB51H3",
        "BIOC65H3<AND-CHMA10H3-CHMA11H3",
        "BIOC65H3<BIOB50H3",
        "BIOD25H3<BIOC15H3",
        "BIOD33H3<BIOC34H3",
        "BIOD37H3<BIOB11H3",
        "BIOD43H3<BIOC34H3",
        "BIOD48H3<BIOB50H3",
        "BIOD48H3<BIOB51H3",
        "BIOD53H3<BIOC54H3",
        "BIOD55H3<BIOC54H3",
        "BIOD59H3<BIOB50H3",
        "BIOD60H3<BIOB50H3",
        "BIOD60H3<STAB22H3",
        "BIOD63H3<BIOB50H3",
        "BIOD63H3<BIOB51H3",
        "BIOD66H3<BIOB51H3",
        "EESC04H3<BIOB50H3",
        "EESC30H3<BIOB50H3",
        "EESC30H3<BIOB51H3",
        "EESC30H3<AND-CHMA10H3-CHMA11H3",
        "AND-BIOA01H3-BIOA02H3<BIOA01H3",
        "AND-BIOA01H3-BIOA02H3<BIOA02H3",
        "AND-CHMA10H3-CHMA11H3<CHMA10H3",
        "AND-CHMA10H3-CHMA11H3<CHMA11H3",
        "AND-MATA29,35<MATA29H3",
        "AND-MATA29,35<MATA35H3",
        "AND-MATA30,36<MATA30H3",
        "AND-MATA30,36<MATA36H3",
        "OR-MA1-MA2<AND-MATA29,35",
        "OR-MA1-MA2<AND-MATA30,36",
        "OR-PHYA10H3-PHYA11H3<PHYA10H3",
        "OR-PHYA10H3-PHYA11H3<PHYA11H3",
        "OR-STAB22H3-PSYB07H3<STAB22H3",
        "OR-STAB22H3-PSYB07H3<PSYB07H3",
        "OR-CSCA08H3-CSCA20H3-PSCB57H3<CSCA08H3",
        "OR-CSCA08H3-CSCA20H3-PSCB57H3<CSCA20H3",
        "OR-CSCA08H3-CSCA20H3-PSCB57H3<PSCB57H3"
      ],
      "correq":[
        "BIOB52H3<BIOB50H3",
        "BIOB52H3<BIOB51H3",
        "BIOC52H3<BIOB50H3",
        "BIOC52H3<BIOB51H3"
      ],
      "recommend":[
        "BIOB34H3<MATA29H3",
        "BIOC16H3<BIOC15H3"
      ],
      "orpre":[
        "BIOC34H3<BIOB34H3",
        "BIOC34H3<NROB60H3",
        "BIOC37H3<BIOB38H3",
        "BIOC37H3<BIOB50H3",
        "BIOC37H3<BIOB51H3",
        "BIOC60H3<BIOB50H3",
        "BIOC60H3<BIOB51H3",
        "NROC34H3<NROB60H3",
        "NROC34H3<BIOB34H3",
        "BIOD26H3<BIOC17H3",
        "BIOD26H3<BIOC39H3",
        "BIOD37H3<BIOC31H3",
        "BIOD37H3<BIOC40H3",
        "BIOD45H3<BIOC54H3",
        "BIOD45H3<NROC34H3",
        "BIOD48H3<BIOC50H3",
        "BIOD48H3<BIOC54H3",
        "BIOD48H3<BIOC61H3",
        "BIOD52H3<BIOC50H3",
        "BIOD52H3<BIOC63H3",
        "BIOD54H3<BIOC62H3",
        "BIOD54H3<BIOC63H3",
        "BIOD59H3<MATA29H3",
        "BIOD59H3<MATA30H3",
        "BIOD60H3<BIOC59H3",
        "BIOD60H3<BIOC61H3",
        "BIOD62H3<BIOC16H3",
        "BIOD62H3<BIOC50H3",
        "BIOD63H3<BIOC51H3",
        "BIOD63H3<BIOC52H3",
        "BIOD63H3<BIOC54H3",
        "BIOD63H3<BIOC58H3",
        "BIOD63H3<BIOC59H3",
        "BIOD63H3<BIOC60H3",
        "BIOD63H3<BIOC61H3",
        "BIOD66H3<BIOC59H3",
        "BIOD66H3<BIOC61H3"
      ]
    }
  },
  "sp-ibs":{
    "nodes":{
      "First Year":[
        "BIOA01H3",
        "BIOA02H3",
        "CHMA10H3",
        "CHMA11H3",
        "MATA29H3",
        "MATA35H3",
        "MATA30H3",
        "MATA36H3",
        "PHYA10H3",
        "PHYA11H3",
        "CSCA08H3",
        "CSCA20H3",
        "PSCB57H3",
        "AND-BIOA01H3-BIOA02H3",
        "AND-CHMA10H3-CHMA11H3",
        "AND-MATA29,35",
        "AND-MATA30,36",
        "OR-MA1-MA2",
        "OR-PHYA10H3-PHYA11H3",
        "OR-STAB22H3-PSYB07H3",
        "OR-CSCA08H3-CSCA20H3-PSCB57H3"
      ],
      "Second Year":[
        "BIOB10H3",
        "BIOB11H3",
        "BIOB34H3",
        "BIOB38H3",
        "BIOB50H3",
        "BIOB51H3",
        "BIOB12H3",
        "BIOB32H3",
        "BIOB33H3",
        "BIOB52H3",
        "STAB22H3",
        "PSYB07H3",
        "CHMB41H3",
        "ANTB22H3",
        "NROB60H3"
      ],
      "Third Year":[
        "BIOC15H3",
        "BIOC17H3",
        "BIOC54H3"
      ],
      "PBN":[
        "BIOC12H3",
        "BIOC13H3",
        "BIOC23H3",
        "BIOC32H3",
        "BIOC34H3",
        "BIOC39H3",
        "BIOC40H3",
        "BIOC65H3",
        "ANTC67H3",
        "NROC34H3",
        "NROC61H3",
        "NROC64H3",
        "PSYC31H3",
        "BIOD07H3",
        "BIOD08H3",
        "BIOD12H3",
        "BIOD27H3",
        "BIOD29H3",
        "BIOD35H3",
        "BIOD43H3",
        "BIOD65H3",
        "NROD67H3"
      ],
      "CEC":[
        "BIOC50H3",
        "BIOC51H3",
        "BIOC52H3",
        "BIOC58H3",
        "BIOC59H3",
        "BIOC61H3",
        "BIOC62H3",
        "BIOC63H3",
        "EESC04H3",
        "BIOD52H3",
        "BIOD54H3",
        "BIOD55H3",
        "BIOD59H3",
        "BIOD60H3",
        "BIOD62H3",
        "BIOD63H3",
        "BIOD66H3",
        "BIOD67H3"
      ],
      "CGD":[
        "BIOC10H3",
        "BIOC14H3",
        "BIOC16H3",
        "BIOC19H3",
        "BIOC31H3",
        "BIOD19H3",
        "BIOD21H3",
        "BIOD22H3",
        "BIOD23H3",
        "BIOD25H3"
      ],
      "OB":[
        "BIOC20H3",
        "BIOC21H3",
        "BIOC35H3",
        "ANTD22H3",
        "ANTC68H3",
        "EESC30H3",
        "BIOC37H3",
        "BIOC60H3",
        "BIOD17H3",
        "BIOD20H3",
        "BIOD26H3",
        "BIOD33H3",
        "BIOD37H3",
        "BIOD45H3",
        "BIOD48H3",
        "BIOD53H3"
      ]
    },
    "edges":{
      "andpre":[
        "BIOB10H3<AND-BIOA01H3-BIOA02H3",
        "BIOB10H3<AND-CHMA10H3-CHMA11H3",
        "BIOB11H3<BIOB10H3",
        "BIOB12H3<AND-CHMA10H3-CHMA11H3",
        "BIOB33H3<AND-BIOA01H3-BIOA02H3",
        "BIOB34H3<AND-BIOA01H3-BIOA02H3",
        "BIOB34H3<AND-CHMA10H3-CHMA11H3",
        "BIOB38H3<AND-BIOA01H3-BIOA02H3",
        "BIOB50H3<AND-BIOA01H3-BIOA02H3",
        "BIOB51H3<AND-BIOA01H3-BIOA02H3",
        "BIOB52H3<AND-BIOA01H3-BIOA02H3",
        "BIOC10H3<BIOB11H3",
        "BIOC12H3<BIOB11H3",
        "BIOC12H3<CHMB41H3",
        "BIOC13H3<BIOB11H3",
        "BIOC13H3<CHMB41H3",
        "BIOC14H3<BIOB11H3",
        "BIOC15H3<BIOB11H3",
        "BIOC15H3<OR-STAB22H3-PSYB07H3",
        "BIOC16H3<BIOB51H3",
        "BIOC17H3<BIOB11H3",
        "BIOC19H3<BIOB11H3",
        "BIOC20H3<BIOB11H3",
        "BIOC21H3<BIOB10H3",
        "BIOC21H3<BIOB34H3",
        "BIOC23H3<BIOB12H3",
        "BIOC23H3<BIOC12H3",
        "BIOC35H3<BIOB11H3",
        "BIOC39H3<BIOB11H3",
        "BIOC31H3<BIOB11H3",
        "BIOC40H3<BIOB11H3",
        "BIOC50H3<BIOB50H3",
        "BIOC51H3<BIOB50H3",
        "BIOC51H3<BIOB51H3",
        "BIOC51H3<BIOB52H3",
        "BIOC54H3<BIOB50H3",
        "BIOC54H3<BIOB51H3",
        "BIOC58H3<BIOB50H3",
        "BIOC58H3<BIOB51H3",
        "BIOC59H3<BIOB50H3",
        "BIOC61H3<BIOB50H3",
        "BIOC62H3<BIOB50H3",
        "BIOC62H3<BIOB51H3",
        "BIOC63H3<BIOB50H3",
        "BIOC63H3<BIOB51H3",
        "BIOC65H3<AND-CHMA10H3-CHMA11H3",
        "BIOC65H3<BIOB50H3",
        "EESC04H3<BIOB50H3",
        "EESC30H3<BIOB50H3",
        "EESC30H3<BIOB51H3",
        "EESC30H3<AND-CHMA10H3-CHMA11H3",
        "PSYC31H3<OR-STAB22H3-PSYB07H3",
        "BIOD08H3<OR-STAB22H3-PSYB07H3",
        "BIOD19H3<BIOC14H3",
        "BIOD20H3<BIOC20H3",
        "BIOD21H3<BIOB12H3",
        "BIOD21H3<BIOC15H3",
        "BIOD21H3<BIOC17H3",
        "BIOD23H3<BIOC12H3",
        "BIOD25H3<BIOC15H3",
        "BIOD33H3<BIOC34H3",
        "BIOD35H3<BIOC34H3",
        "BIOD37H3<BIOB11H3",
        "BIOD43H3<BIOC34H3",
        "BIOD48H3<BIOB50H3",
        "BIOD48H3<BIOB51H3",
        "BIOD53H3<BIOC54H3",
        "BIOD55H3<BIOC54H3",
        "BIOD59H3<BIOB50H3",
        "BIOD60H3<BIOB50H3",
        "BIOD60H3<STAB22H3",
        "BIOD63H3<BIOB50H3",
        "BIOD63H3<BIOB51H3",
        "BIOD65H3<BIOB11H3",
        "BIOD66H3<BIOB51H3",
        "NROD67H3<NROB60H3",
        "ANTD22H3<ANTB22H3",
        "AND-BIOA01H3-BIOA02H3<BIOA01H3",
        "AND-BIOA01H3-BIOA02H3<BIOA02H3",
        "AND-CHMA10H3-CHMA11H3<CHMA10H3",
        "AND-CHMA10H3-CHMA11H3<CHMA11H3",
        "AND-MATA29,35<MATA29H3",
        "AND-MATA29,35<MATA35H3",
        "AND-MATA30,36<MATA30H3",
        "AND-MATA30,36<MATA36H3",
        "OR-MA1-MA2<AND-MATA29,35",
        "OR-MA1-MA2<AND-MATA30,36",
        "OR-PHYA10H3-PHYA11H3<PHYA10H3",
        "OR-PHYA10H3-PHYA11H3<PHYA11H3",
        "OR-STAB22H3-PSYB07H3<STAB22H3",
        "OR-STAB22H3-PSYB07H3<PSYB07H3",
        "OR-CSCA08H3-CSCA20H3-PSCB57H3<CSCA08H3",
        "OR-CSCA08H3-CSCA20H3-PSCB57H3<CSCA20H3",
        "OR-CSCA08H3-CSCA20H3-PSCB57H3<PSCB57H3"
      ],
      "correq":[
        "BIOB12H3<BIOB11H3",
        "BIOB32H3<BIOB34H3",
        "BIOB52H3<BIOB50H3",
        "BIOB52H3<BIOB51H3",
        "BIOC52H3<BIOB50H3",
        "BIOC52H3<BIOB51H3",
        "BIOD21H3<BIOC12H3"
      ],
      "recommend":[
        "BIOB34H3<MATA29H3",
        "BIOC10H3<BIOC12H3",
        "BIOC16H3<BIOC15H3",
        "BIOD27H3<BIOC34H3"
      ],
      "orpre":[
        "BIOC32H3<BIOB34H3",
        "BIOC32H3<NROB60H3",
        "BIOC34H3<BIOB34H3",
        "BIOC34H3<NROB60H3",
        "BIOC37H3<BIOB38H3",
        "BIOC37H3<BIOB50H3",
        "BIOC37H3<BIOB51H3",
        "BIOC60H3<BIOB50H3",
        "BIOC60H3<BIOB51H3",
        "NROC34H3<NROB60H3",
        "NROC34H3<BIOB34H3",
        "NROC61H3<NROB60H3",
        "NROC64H3<NROB60H3",
        "BIOD07H3<BIOC32H3",
        "BIOD07H3<NROC34H3",
        "BIOD07H3<NROC64H3",
        "BIOD08H3<MATA29H3",
        "BIOD08H3<MATA30H3",
        "BIOD08H3<NROC34H3",
        "BIOD08H3<NROC64H3",
        "BIOD12H3<BIOC10H3",
        "BIOD12H3<BIOC12H3",
        "BIOD17H3<BIOC17H3",
        "BIOD17H3<BIOC39H3",
        "BIOD22H3<BIOC10H3",
        "BIOD22H3<BIOC12H3",
        "BIOD22H3<BIOC15H3",
        "BIOD26H3<BIOC17H3",
        "BIOD26H3<BIOC39H3",
        "BIOD27H3<BIOB34H3",
        "BIOD27H3<BIOC32H3",
        "BIOD29H3<BIOC10H3",
        "BIOD29H3<BIOC20H3",
        "BIOD29H3<BIOC39H3",
        "BIOD37H3<BIOC31H3",
        "BIOD37H3<BIOC40H3",
        "BIOD45H3<BIOC54H3",
        "BIOD45H3<NROC34H3",
        "BIOD48H3<BIOC50H3",
        "BIOD48H3<BIOC54H3",
        "BIOD48H3<BIOC61H3",
        "BIOD52H3<BIOC50H3",
        "BIOD52H3<BIOC63H3",
        "BIOD54H3<BIOC62H3",
        "BIOD54H3<BIOC63H3",
        "BIOD59H3<MATA29H3",
        "BIOD59H3<MATA30H3",
        "BIOD60H3<BIOC59H3",
        "BIOD60H3<BIOC61H3",
        "BIOD62H3<BIOC16H3",
        "BIOD62H3<BIOC50H3",
        "BIOD63H3<BIOC51H3",
        "BIOD63H3<BIOC52H3",
        "BIOD63H3<BIOC54H3",
        "BIOD63H3<BIOC58H3",
        "BIOD63H3<BIOC59H3",
        "BIOD63H3<BIOC60H3",
        "BIOD63H3<BIOC61H3",
        "BIOD65H3<BIOC32H3",
        "BIOD65H3<NROC61H3",
        "BIOD65H3<NROC64H3",
        "BIOD66H3<BIOC59H3",
        "BIOD66H3<BIOC61H3",
        "NROD67H3<NROC61H3",
        "NROD67H3<NROC64H3"
      ]
    }
  }
}